pycmark/__init__.py
pycmark/addnodes.py
pycmark/cli.py
pycmark/readers.py
pycmark/transforms.py
pycmark/blockparser/__init__.py
pycmark/blockparser/container_processors.py
pycmark/blockparser/html_processors.py
pycmark/blockparser/link_processors.py
pycmark/blockparser/std_processors.py
pycmark/inlineparser/__init__.py
pycmark/inlineparser/link_processors.py
pycmark/inlineparser/std_processors.py
pycmark/utils/__init__.py
pycmark/utils/compat.py
pycmark/utils/entitytrans.py
pycmark-0.9.6.dist-info/LICENSE
pycmark-0.9.6.dist-info/METADATA
pycmark-0.9.6.dist-info/WHEEL
pycmark-0.9.6.dist-info/entry_points.txt
pycmark-0.9.6.dist-info/top_level.txt
pycmark-0.9.6.dist-info/RECORD
